kiara_plugin/develop/__init__.py
kiara_plugin/develop/data_types.py
kiara_plugin/develop/defaults.py
kiara_plugin/develop/models.py
kiara_plugin/develop/py.typed
kiara_plugin/develop/version.txt
kiara_plugin/develop/interfaces/__init__.py
kiara_plugin/develop/interfaces/cli/__init__.py
kiara_plugin/develop/interfaces/cli/debug.py
kiara_plugin/develop/interfaces/cli/dev.py
kiara_plugin/develop/interfaces/cli/pkg_build.py
kiara_plugin/develop/modules/__init__.py
kiara_plugin/develop/modules/pipelines/__init__.py
kiara_plugin/develop/pipelines/.gitkeep
kiara_plugin/develop/pipelines/__init__.py
kiara_plugin/develop/pkg_build/__init__.py
kiara_plugin/develop/pkg_build/models.py
kiara_plugin/develop/pkg_build/states.py
kiara_plugin/develop/pkg_build/conda/__init__.py
kiara_plugin/develop/pkg_build/conda/states.py
kiara_plugin/develop/pkg_build/rattler/__init__.py
kiara_plugin/develop/pkg_build/rattler/models.py
kiara_plugin/develop/pkg_build/rattler/states.py
kiara_plugin/develop/resources/.gitkeep
kiara_plugin/develop/resources/scripts/build-conda-packages.sh
kiara_plugin/develop/resources/templates/meta.yaml.j2
kiara_plugin/develop/resources/templates/rattler-build-recipe.yaml.j2
kiara_plugin/develop/resources/templates/recipe.yaml.j2
kiara_plugin/develop/resources/templates/flatbuffers/schema_def.fbs.j2
kiara_plugin/develop/schema/__init__.py
kiara_plugin/develop/schema/flatbuffers.py
kiara_plugin/develop/schema/javascript.py
kiara_plugin/develop/utils/__init__.py
kiara_plugin/develop/utils/pkg_utils.py
kiara_plugin.develop-0.5.3.dist-info/AUTHORS.md
kiara_plugin.develop-0.5.3.dist-info/LICENSE
kiara_plugin.develop-0.5.3.dist-info/METADATA
kiara_plugin.develop-0.5.3.dist-info/WHEEL
kiara_plugin.develop-0.5.3.dist-info/entry_points.txt
kiara_plugin.develop-0.5.3.dist-info/top_level.txt
kiara_plugin.develop-0.5.3.dist-info/RECORD
