Metadata-Version: 2.1
Name: kiara_plugin.develop
Version: 0.5.3
Summary: Development utilities for kiara.
Author-email: Markus Binsteiner <markus@frkl.io>
License: MPL-2.0
Project-URL: homepage, https://github.com/DHARPA-Project/kiara_plugin.develop
Project-URL: documentation, https://DHARPA-Project.github.io/kiara_plugin.develop
Project-URL: repository, https://github.com/DHARPA-Project/kiara_plugin.develop
Keywords: kiara
Classifier: Programming Language :: Python :: 3
Classifier: Development Status :: 3 - Alpha
Classifier: License :: OSI Approved :: Mozilla Public License 2.0 (MPL 2.0)
Classifier: Programming Language :: Python
Classifier: Programming Language :: Python :: 3
Classifier: Programming Language :: Python :: 3 :: Only
Classifier: Programming Language :: Python :: 3.9
Classifier: Programming Language :: Python :: 3.10
Classifier: Programming Language :: Python :: 3.11
Classifier: Programming Language :: Python :: 3.12
Requires-Python: >=3.9
License-File: LICENSE
License-File: AUTHORS.md
Requires-Dist: kiara<0.6.0,>=0.5.13
Requires-Dist: kiara_plugin.core_types<0.6.0,>=0.5.2
Requires-Dist: build>=1.2.1
Requires-Dist: diskcache>=5.4.0
Requires-Dist: httpx>=0.23.0
Requires-Dist: pydantic-to-typescript>=1.0.10
Requires-Dist: license-expression>=30.1.0
Requires-Dist: setuptools>=64
Requires-Dist: setuptools_scm[toml]>8
Requires-Dist: wheel
Provides-Extra: dev-documentation
Requires-Dist: kiara[dev_documentation]; extra == "dev-documentation"
Provides-Extra: dev-testing
Requires-Dist: kiara[dev_testing]; extra == "dev-testing"
Provides-Extra: dev-utils
Requires-Dist: kiara[dev_utils]; extra == "dev-utils"
